README.md
setup.cfg
setup.py
amino/__init__.py
amino/client.py
amino/community_client.py
amino/socket.py
amino.api.egg-info/PKG-INFO
amino.api.egg-info/SOURCES.txt
amino.api.egg-info/dependency_links.txt
amino.api.egg-info/requires.txt
amino.api.egg-info/top_level.txt
amino/asynclib/__init__.py
amino/asynclib/client.py
amino/asynclib/community_client.py
amino/asynclib/socket.py
amino/helpers/__init__.py
amino/helpers/exceptions.py
amino/helpers/generators.py
amino/helpers/headers.py
amino/helpers/requester.py
amino/helpers/types.py
amino/models/__init__.py
amino/models/objects.py
amino/models/proxy_settings.py