Metadata-Version: 2.1
Name: amino.api
Version: 0.2.5.6
Summary: Library for creating amino bots and scripts.
Home-page: https://github.com/xXxCLOTIxXx/amino.py
Author: Xsarz
Author-email: xsarzy@gmail.com
License: MIT
Download-URL: https://github.com/xXxCLOTIxXx/amino.py/archive/refs/heads/main.zip
Keywords: aminoapps,aminoxz,amino,amino-bot,pymino,python-amino,amino.py,amino.api,narvii,api,python,python3,python3.x,xsarz,official
Platform: UNKNOWN
